Metadata-Version: 1.0
Name: chazutsu
Version: 0.8.2
Summary: The tool to make NLP datasets ready to use
Home-page: https://github.com/chakki-works/chazutsu
Author: icoxfog417
Author-email: icoxfog417@yahoo.co.jp
License: Apache License 2.0
Keywords: machine learning,nlp,natural language processing
Platform: UNKNOWN
